gobbet/__init__.py
gobbet/downloader.py
gobbet/parser.py
gobbet/wordlist.py
gobbet-0.0.3.dist-info/LICENSE
gobbet-0.0.3.dist-info/METADATA
gobbet-0.0.3.dist-info/WHEEL
gobbet-0.0.3.dist-info/top_level.txt
gobbet-0.0.3.dist-info/RECORD
