Metadata-Version: 2.1
Name: gobbet
Version: 0.0.3
Summary: Random news articles in any language
Home-page: https://github.com/simoncozens/gobbet
Author: Simon Cozens
Author-email: simon@simon-cozens.org
License: MIT
Platform: UNKNOWN
Classifier: Programming Language :: Python
Classifier: Programming Language :: Python :: 2
Classifier: Programming Language :: Python :: 3
Classifier: License :: OSI Approved :: MIT License
Classifier: Development Status :: 4 - Beta
License-File: LICENSE
Requires-Dist: tqdm
Requires-Dist: mwparserfromhell
Requires-Dist: orjson
Requires-Dist: nltk
Requires-Dist: htmllistparse
Requires-Dist: youseedee
